{"pause": 0.5, "keys": [{"key": "hv", "pause": 0.5}, {"key": "ezc-", "pause": 0.25}, {"key": "w-", "pause": 0.25}, {"key": "e", "pause": 0.5}, {"key": "e>", "pause": 1.5}, {"key": "gv", "pause": 0.5}, {"key": "wms-", "pause": 0.25}, {"key": "q-", "pause": 0.25}, {"key": "w", "pause": 0.5}, {"key": "w>", "pause": 1.5}, {"key": "gc", "pause": 0.5}, {"key": "wms-", "pause": 0.25}, {"key": "q-", "pause": 0.25}, {"key": "w", "pause": 0.5}, {"key": "w>", "pause": 1.5}, {"key": "ty", "pause": 0.5}, {"key": "qad-", "pause": 0.25}, {"key": "j-", "pause": 0.25}, {"key": "q", "pause": 0.5}, {"key": "q>", "pause": 1.5}, {"key": "hv", "pause": 0.5}, {"key": "ead-", "pause": 0.25}, {"key": "w-", "pause": 0.25}, {"key": "e", "pause": 0.5}, {"key": "wad", "pause": 0.5}, {"key": "eda", "pause": 0.5}, {"key": "yda", "pause": 0.5}, {"key": "e", "pause": 0.5}, {"key": "wda", "pause": 0.5}, {"key": "ev-", "pause": 0.25}, {"key": "w-", "pause": 0.25}, {"key": "ems-", "pause": 0.25}, {"key": "w-", "pause": 0.25}, {"key": "e", "pause": 0.5}, {"key": "wsm", "pause": 0.5}, {"key": "gms", "pause": 0.5}, {"key": "s", "pause": 0.5}, {"key": "m", "pause": 0.5}, {"key": "b", "pause": 0.5}, {"key": "gc", "pause": 0.5}, {"key": "wms-", "pause": 0.25}, {"key": "q-", "pause": 0.25}, {"key": "w", "pause": 0.5}, {"key": "qms", "pause": 0.5}, {"key": "wms", "pause": 0.5}, {"key": "tms", "pause": 0.5}, {"key": "t", "pause": 0.5}, {"key": "wms", "pause": 0.5}, {"key": "wn-", "pause": 0.25}, {"key": "e-", "pause": 0.25}, {"key": "wad-", "pause": 0.25}, {"key": "e-", "pause": 0.25}, {"key": "w", "pause": 0.5}, {"key": "jad", "pause": 0.5}, {"key": "q", "pause": 0.5}, {"key": "ad", "pause": 0.5}, {"key": "bm", "pause": 0.5}, {"key": "bx", "pause": 0.5}, {"key": "hv", "pause": 0.5}, {"key": "ead-", "pause": 0.25}, {"key": "w-", "pause": 0.25}, {"key": "e", "pause": 0.5}, {"key": "wad", "pause": 0.5}, {"key": "ead", "pause": 0.5}, {"key": "yad", "pause": 0.5}, {"key": "e", "pause": 0.5}, {"key": "wad", "pause": 0.5}, {"key": "ev-", "pause": 0.25}, {"key": "w-", "pause": 0.25}, {"key": "ems-", "pause": 0.25}, {"key": "w-", "pause": 0.25}, {"key": "e", "pause": 0.5}, {"key": "wms", "pause": 0.5}, {"key": "tms", "pause": 0.5}, {"key": "s", "pause": 0.5}, {"key": "m", "pause": 0.5}, {"key": "b", "pause": 0.5}, {"key": "gc", "pause": 0.5}, {"key": "wms-", "pause": 0.25}, {"key": "q-", "pause": 0.25}, {"key": "w", "pause": 0.5}, {"key": "qms", "pause": 0.5}, {"key": "wms", "pause": 0.5}, {"key": "tms", "pause": 0.5}, {"key": "t", "pause": 0.5}, {"key": "u", "pause": 0.5}, {"key": "ycn-", "pause": 0.25}, {"key": "u-", "pause": 0.25}, {"key": "yd-", "pause": 0.25}, {"key": "u-", "pause": 0.25}, {"key": "yq", "pause": 0.5}, {"key": "t", "pause": 0.5}, {"key": "y>", "pause": 1.5}, {"key": "hv-", "pause": 0.25}, {"key": "ead_", "pause": 0.125}, {"key": "w_", "pause": 0.125}, {"key": "e-", "pause": 0.25}, {"key": "ad-", "pause": 0.25}, {"key": "v-", "pause": 0.25}, {"key": "ad", "pause": 0.5}, {"key": "ad-", "pause": 0.25}, {"key": "gc-", "pause": 0.25}, {"key": "wsj_", "pause": 0.125}, {"key": "q_", "pause": 0.125}, {"key": "w-", "pause": 0.25}, {"key": "sm-", "pause": 0.25}, {"key": "c-", "pause": 0.25}, {"key": "sm", "pause": 0.5}, {"key": "sm-", "pause": 0.25}, {"key": "gc-", "pause": 0.25}, {"key": "wsj_", "pause": 0.125}, {"key": "q_", "pause": 0.125}, {"key": "w-", "pause": 0.25}, {"key": "sm-", "pause": 0.25}, {"key": "c-", "pause": 0.25}, {"key": "sm", "pause": 0.5}, {"key": "sm-", "pause": 0.25}, {"key": "tn-", "pause": 0.25}, {"key": "qad_", "pause": 0.125}, {"key": "j_", "pause": 0.125}, {"key": "q-", "pause": 0.25}, {"key": "ad-", "pause": 0.25}, {"key": "cn-", "pause": 0.25}, {"key": "ad-", "pause": 0.25}, {"key": "bx-", "pause": 0.25}, {"key": "sm-", "pause": 0.25}, {"key": "hv-", "pause": 0.25}, {"key": "ead_", "pause": 0.125}, {"key": "w_", "pause": 0.125}, {"key": "e-", "pause": 0.25}, {"key": "ad-", "pause": 0.25}, {"key": "v-", "pause": 0.25}, {"key": "ad", "pause": 0.5}, {"key": "ad-", "pause": 0.25}, {"key": "yv-", "pause": 0.25}, {"key": "wms_", "pause": 0.125}, {"key": "q_", "pause": 0.125}, {"key": "w-", "pause": 0.25}, {"key": "ms-", "pause": 0.25}, {"key": "v-", "pause": 0.25}, {"key": "ms", "pause": 0.5}, {"key": "ms-", "pause": 0.25}, {"key": "uc-", "pause": 0.25}, {"key": "wsm_", "pause": 0.125}, {"key": "q_", "pause": 0.125}, {"key": "w-", "pause": 0.25}, {"key": "ms-", "pause": 0.25}, {"key": "c-", "pause": 0.25}, {"key": "ms", "pause": 0.5}, {"key": "ms-", "pause": 0.25}, {"key": "eqn-", "pause": 0.25}, {"key": "w-", "pause": 0.25}, {"key": "y-", "pause": 0.25}, {"key": "c-", "pause": 0.25}, {"key": "nad", "pause": 0.5}, {"key": "bx", "pause": 0.5}, {"key": "nv-", "pause": 0.25}, {"key": "da_", "pause": 0.125}, {"key": "w_", "pause": 0.125}, {"key": "d-", "pause": 0.25}, {"key": "sa-", "pause": 0.25}, {"key": "dv-", "pause": 0.25}, {"key": "ha-", "pause": 0.25}, {"key": "d-", "pause": 0.25}, {"key": "sa-", "pause": 0.25}, {"key": "dv_", "pause": 0.125}, {"key": "s_", "pause": 0.125}, {"key": "dm_", "pause": 0.125}, {"key": "s_", "pause": 0.125}, {"key": "d-", "pause": 0.25}, {"key": "sm-", "pause": 0.25}, {"key": "bv-", "pause": 0.25}, {"key": "sm-", "pause": 0.25}, {"key": "m-", "pause": 0.25}, {"key": "b-", "pause": 0.25}, {"key": "bc-", "pause": 0.25}, {"key": "sb_", "pause": 0.125}, {"key": "a_", "pause": 0.125}, {"key": "s-", "pause": 0.25}, {"key": "ab-", "pause": 0.25}, {"key": "sc-", "pause": 0.25}, {"key": "gb-", "pause": 0.25}, {"key": "g-", "pause": 0.25}, {"key": "sb-", "pause": 0.25}, {"key": "sn_", "pause": 0.125}, {"key": "d_", "pause": 0.125}, {"key": "sa_", "pause": 0.125}, {"key": "d_", "pause": 0.125}, {"key": "s-", "pause": 0.25}, {"key": "mn-", "pause": 0.25}, {"key": "acn", "pause": 0.5}, {"key": "mbx", "pause": 0.5}, {"key": "nv-", "pause": 0.25}, {"key": "da_", "pause": 0.125}, {"key": "s_", "pause": 0.125}, {"key": "d-", "pause": 0.25}, {"key": "sa-", "pause": 0.25}, {"key": "dv-", "pause": 0.25}, {"key": "ha-", "pause": 0.25}, {"key": "d-", "pause": 0.25}, {"key": "sa-", "pause": 0.25}, {"key": "dv_", "pause": 0.125}, {"key": "s_", "pause": 0.125}, {"key": "dm_", "pause": 0.125}, {"key": "s_", "pause": 0.125}, {"key": "d-", "pause": 0.25}, {"key": "sm-", "pause": 0.25}, {"key": "bv-", "pause": 0.25}, {"key": "sm-", "pause": 0.25}, {"key": "m-", "pause": 0.25}, {"key": "b-", "pause": 0.25}, {"key": "bc-", "pause": 0.25}, {"key": "sb_", "pause": 0.125}, {"key": "a_", "pause": 0.125}, {"key": "s-", "pause": 0.25}, {"key": "ab-", "pause": 0.25}, {"key": "sc-", "pause": 0.25}, {"key": "gb-", "pause": 0.25}, {"key": "g-", "pause": 0.25}, {"key": "jb-", "pause": 0.25}, {"key": "hn_", "pause": 0.125}, {"key": "j_", "pause": 0.125}, {"key": "h_", "pause": 0.125}, {"key": "j_", "pause": 0.125}, {"key": "hn-", "pause": 0.25}, {"key": "gc-", "pause": 0.25}, {"key": "hnc", "pause": 0.5}, {"key": "xb", "pause": 0.5}, {"key": "hv-", "pause": 0.25}, {"key": "eda_", "pause": 0.125}, {"key": "w_", "pause": 0.125}, {"key": "e-", "pause": 0.25}, {"key": "wad-", "pause": 0.25}, {"key": "ev-", "pause": 0.25}, {"key": "yda-", "pause": 0.25}, {"key": "e-", "pause": 0.25}, {"key": "wad-", "pause": 0.25}, {"key": "ev_", "pause": 0.125}, {"key": "w_", "pause": 0.125}, {"key": "esm_", "pause": 0.125}, {"key": "w_", "pause": 0.125}, {"key": "e-", "pause": 0.25}, {"key": "wsm-", "pause": 0.25}, {"key": "gv-", "pause": 0.25}, {"key": "wsm-", "pause": 0.25}, {"key": "j-", "pause": 0.25}, {"key": "gsm-", "pause": 0.25}, {"key": "gc-", "pause": 0.25}, {"key": "wsm_", "pause": 0.125}, {"key": "q_", "pause": 0.125}, {"key": "w-", "pause": 0.25}, {"key": "qsm-", "pause": 0.25}, {"key": "wc-", "pause": 0.25}, {"key": "tsm-", "pause": 0.25}, {"key": "t-", "pause": 0.25}, {"key": "wsm-", "pause": 0.25}, {"key": "wn_", "pause": 0.125}, {"key": "e_", "pause": 0.125}, {"key": "wda_", "pause": 0.125}, {"key": "e_", "pause": 0.125}, {"key": "w-", "pause": 0.25}, {"key": "jda-", "pause": 0.25}, {"key": "qnc-", "pause": 0.25}, {"key": "ad-", "pause": 0.25}, {"key": "jxb-", "pause": 0.25}, {"key": "sm-", "pause": 0.25}, {"key": "hv-", "pause": 0.25}, {"key": "ead_", "pause": 0.125}, {"key": "w_", "pause": 0.125}, {"key": "e-", "pause": 0.25}, {"key": "wad-", "pause": 0.25}, {"key": "ev-", "pause": 0.25}, {"key": "yad-", "pause": 0.25}, {"key": "e-", "pause": 0.25}, {"key": "wad-", "pause": 0.25}, {"key": "ev_", "pause": 0.125}, {"key": "w_", "pause": 0.125}, {"key": "ems_", "pause": 0.125}, {"key": "w_", "pause": 0.125}, {"key": "e-", "pause": 0.25}, {"key": "esm-", "pause": 0.25}, {"key": "gv-", "pause": 0.25}, {"key": "wsm-", "pause": 0.25}, {"key": "j-", "pause": 0.25}, {"key": "gsm-", "pause": 0.25}, {"key": "gc-", "pause": 0.25}, {"key": "wsm_", "pause": 0.125}, {"key": "q_", "pause": 0.125}, {"key": "w-", "pause": 0.25}, {"key": "qms-", "pause": 0.25}, {"key": "wc-", "pause": 0.25}, {"key": "tsm-", "pause": 0.25}, {"key": "t-", "pause": 0.25}, {"key": "usm-", "pause": 0.25}, {"key": "yn_", "pause": 0.125}, {"key": "u_", "pause": 0.125}, {"key": "yda_", "pause": 0.125}, {"key": "u_", "pause": 0.125}, {"key": "y-", "pause": 0.25}, {"key": "tda-", "pause": 0.25}, {"key": "yn", "pause": 0.5}, {"key": "hanc-", "pause": 0.25}, {"key": "j-", "pause": 0.25}, {"key": "qax-", "pause": 0.25}, {"key": "n-", "pause": 0.25}, {"key": "a-", "pause": 0.25}, {"key": "d-", "pause": 0.25}, {"key": "h-", "pause": 0.25}, {"key": "d-", "pause": 0.25}, {"key": "dea-", "pause": 0.25}, {"key": "n-", "pause": 0.25}, {"key": "den-", "pause": 0.25}, {"key": "x-", "pause": 0.25}, {"key": "m-", "pause": 0.25}, {"key": "ws-", "pause": 0.25}, {"key": "wf-", "pause": 0.25}, {"key": "s-", "pause": 0.25}, {"key": "m-", "pause": 0.25}, {"key": "b-", "pause": 0.25}, {"key": "jz-", "pause": 0.25}, {"key": "b-", "pause": 0.25}, {"key": "m-", "pause": 0.25}, {"key": "gs-", "pause": 0.25}, {"key": "gd-", "pause": 0.25}, {"key": "m-", "pause": 0.25}, {"key": "b-", "pause": 0.25}, {"key": "z-", "pause": 0.25}, {"key": "ev-", "pause": 0.25}, {"key": "z-", "pause": 0.25}, {"key": "n-", "pause": 0.25}, {"key": "wda-", "pause": 0.25}, {"key": "e-", "pause": 0.25}, {"key": "q-", "pause": 0.25}, {"key": "hvz-", "pause": 0.25}, {"key": "e-", "pause": 0.25}, {"key": "rmv", "pause": 0.5}, {"key": "s-", "pause": 0.25}, {"key": "f-", "pause": 0.25}, {"key": "h-", "pause": 0.25}, {"key": "es-", "pause": 0.25}, {"key": "erm-", "pause": 0.25}, {"key": "v-", "pause": 0.25}, {"key": "tc", "pause": 0.5}, {"key": "m-", "pause": 0.25}, {"key": "rs-", "pause": 0.25}, {"key": "rd-", "pause": 0.25}, {"key": "s-", "pause": 0.25}, {"key": "em-", "pause": 0.25}, {"key": "c-", "pause": 0.25}, {"key": "wn-", "pause": 0.25}, {"key": "c-", "pause": 0.25}, {"key": "n-", "pause": 0.25}, {"key": "qa-", "pause": 0.25}, {"key": "qd-", "pause": 0.25}, {"key": "a-", "pause": 0.25}, {"key": "wn-", "pause": 0.25}, {"key": "c-", "pause": 0.25}, {"key": "ghn-", "pause": 0.25}, {"key": "c-", "pause": 0.25}, {"key": "hn", "pause": 0.5}, {"key": "jm", "pause": 0.5}, {"key": "hanc-", "pause": 0.25}, {"key": "j", "pause": 0.5}, {"key": "qx-", "pause": 0.25}, {"key": "n-", "pause": 0.25}, {"key": "a-", "pause": 0.25}, {"key": "d-", "pause": 0.25}, {"key": "h-", "pause": 0.25}, {"key": "d-", "pause": 0.25}, {"key": "a-", "pause": 0.25}, {"key": "n-", "pause": 0.25}, {"key": "en-", "pause": 0.25}, {"key": "x-", "pause": 0.25}, {"key": "m-", "pause": 0.25}, {"key": "ws-", "pause": 0.25}, {"key": "wf-", "pause": 0.25}, {"key": "s-", "pause": 0.25}, {"key": "m-", "pause": 0.25}, {"key": "b-", "pause": 0.25}, {"key": "rz-", "pause": 0.25}, {"key": "b-", "pause": 0.25}, {"key": "m-", "pause": 0.25}, {"key": "es-", "pause": 0.25}, {"key": "ed-", "pause": 0.25}, {"key": "m-", "pause": 0.25}, {"key": "b-", "pause": 0.25}, {"key": "z-", "pause": 0.25}, {"key": "wf-", "pause": 0.25}, {"key": "z-", "pause": 0.25}, {"key": "n-", "pause": 0.25}, {"key": "qa-", "pause": 0.25}, {"key": "qf-", "pause": 0.25}, {"key": "a-", "pause": 0.25}, {"key": "n-", "pause": 0.25}, {"key": "v-", "pause": 0.25}, {"key": "emv-", "pause": 0.25}, {"key": "w-", "pause": 0.25}, {"key": "w-", "pause": 0.25}, {"key": "hdsm-", "pause": 0.25}, {"key": "hfsm", "pause": 0.5}, {"key": "smv", "pause": 0.5}, {"key": "qmc-", "pause": 0.25}, {"key": "j-", "pause": 0.25}, {"key": "j-", "pause": 0.25}, {"key": "dsmb-", "pause": 0.25}, {"key": "dsmb", "pause": 0.5}, {"key": "wmc-", "pause": 0.25}, {"key": "q-", "pause": 0.25}, {"key": "hnc+", "pause": 1.0}, {"key": "dan-", "pause": 0.25}, {"key": "dan", "pause": 0.5}, {"key": "anc", "pause": 0.5}, {"key": "adhcn+", "pause": 1.0}, {"key": "xb+", "pause": 1.0}, {"key": "hv-", "pause": 0.25}, {"key": "eda_", "pause": 0.125}, {"key": "w_", "pause": 0.125}, {"key": "e-", "pause": 0.25}, {"key": "ad-", "pause": 0.25}, {"key": "v-", "pause": 0.25}, {"key": "ad", "pause": 0.5}, {"key": "ad-", "pause": 0.25}, {"key": "hv-", "pause": 0.25}, {"key": "wsm_", "pause": 0.125}, {"key": "q_", "pause": 0.125}, {"key": "w-", "pause": 0.25}, {"key": "sm-", "pause": 0.25}, {"key": "v-", "pause": 0.25}, {"key": "sm", "pause": 0.5}, {"key": "sm-", "pause": 0.25}, {"key": "gc-", "pause": 0.25}, {"key": "wsm_", "pause": 0.125}, {"key": "q_", "pause": 0.125}, {"key": "w-", "pause": 0.25}, {"key": "sm-", "pause": 0.25}, {"key": "c-", "pause": 0.25}, {"key": "sm", "pause": 0.5}, {"key": "sm-", "pause": 0.25}, {"key": "tn-", "pause": 0.25}, {"key": "qda_", "pause": 0.125}, {"key": "j_", "pause": 0.125}, {"key": "q-", "pause": 0.25}, {"key": "da-", "pause": 0.25}, {"key": "nc-", "pause": 0.25}, {"key": "da-", "pause": 0.25}, {"key": "bx-", "pause": 0.25}, {"key": "sm-", "pause": 0.25}, {"key": "jv-", "pause": 0.25}, {"key": "eda_", "pause": 0.125}, {"key": "w_", "pause": 0.125}, {"key": "e-", "pause": 0.25}, {"key": "da-", "pause": 0.25}, {"key": "v-", "pause": 0.25}, {"key": "da", "pause": 0.5}, {"key": "da-", "pause": 0.25}, {"key": "yv-", "pause": 0.25}, {"key": "wsm_", "pause": 0.125}, {"key": "q_", "pause": 0.125}, {"key": "w-", "pause": 0.25}, {"key": "sm-", "pause": 0.25}, {"key": "v-", "pause": 0.25}, {"key": "sm", "pause": 0.5}, {"key": "sm-", "pause": 0.25}, {"key": "uc-", "pause": 0.25}, {"key": "wsm_", "pause": 0.125}, {"key": "q_", "pause": 0.125}, {"key": "w-", "pause": 0.25}, {"key": "sm-", "pause": 0.25}, {"key": "c-", "pause": 0.25}, {"key": "sm", "pause": 0.5}, {"key": "sm-", "pause": 0.25}, {"key": "eqn-", "pause": 0.25}, {"key": "w-", "pause": 0.25}, {"key": "y-", "pause": 0.25}, {"key": "c-", "pause": 0.25}, {"key": "dan", "pause": 0.5}, {"key": "bs", "pause": 0.5}, {"key": "nv-", "pause": 0.25}, {"key": "da_", "pause": 0.125}, {"key": "s_d-", "pause": 0.25}, {"key": "sa-", "pause": 0.25}, {"key": "dv-", "pause": 0.25}, {"key": "ha-", "pause": 0.25}, {"key": "d-", "pause": 0.25}, {"key": "sa-", "pause": 0.25}, {"key": "dv_", "pause": 0.125}, {"key": "s_", "pause": 0.125}, {"key": "dm_", "pause": 0.125}, {"key": "d-", "pause": 0.25}, {"key": "sm-", "pause": 0.25}, {"key": "bv-", "pause": 0.25}, {"key": "sm-", "pause": 0.25}, {"key": "m-", "pause": 0.25}, {"key": "b-", "pause": 0.25}, {"key": "bc-", "pause": 0.25}, {"key": "sb_", "pause": 0.125}, {"key": "a_", "pause": 0.125}, {"key": "s-", "pause": 0.25}, {"key": "ab-", "pause": 0.25}, {"key": "sc-", "pause": 0.25}, {"key": "gb-", "pause": 0.25}, {"key": "g-", "pause": 0.25}, {"key": "sb-", "pause": 0.25}, {"key": "sn_", "pause": 0.125}, {"key": "d_", "pause": 0.125}, {"key": "sa_", "pause": 0.125}, {"key": "d_", "pause": 0.125}, {"key": "s-", "pause": 0.25}, {"key": "mn-", "pause": 0.25}, {"key": "anc", "pause": 0.5}, {"key": "mbx", "pause": 0.5}, {"key": "mv-", "pause": 0.25}, {"key": "da_", "pause": 0.125}, {"key": "s_", "pause": 0.125}, {"key": "d-", "pause": 0.25}, {"key": "sa-", "pause": 0.25}, {"key": "dv-", "pause": 0.25}, {"key": "ja-", "pause": 0.25}, {"key": "d-", "pause": 0.25}, {"key": "sa-", "pause": 0.25}, {"key": "dv_", "pause": 0.125}, {"key": "s_", "pause": 0.125}, {"key": "dm_", "pause": 0.125}, {"key": "s_", "pause": 0.125}, {"key": "d-", "pause": 0.25}, {"key": "sm-", "pause": 0.25}, {"key": "bv-", "pause": 0.25}, {"key": "sm-", "pause": 0.25}, {"key": "m-", "pause": 0.25}, {"key": "b-", "pause": 0.25}, {"key": "bc-", "pause": 0.25}, {"key": "sb_a_", "pause": 0.125}, {"key": "s-", "pause": 0.25}, {"key": "ab-", "pause": 0.25}, {"key": "sc-", "pause": 0.25}, {"key": "gb-", "pause": 0.25}, {"key": "g-", "pause": 0.25}, {"key": "jb-", "pause": 0.25}, {"key": "hn_", "pause": 0.125}, {"key": "j_", "pause": 0.125}, {"key": "h_", "pause": 0.125}, {"key": "j_", "pause": 0.125}, {"key": "hn-", "pause": 0.25}, {"key": "gc-", "pause": 0.25}, {"key": "hnc", "pause": 0.5}, {"key": "gx", "pause": 0.5}, {"key": "hv-", "pause": 0.25}, {"key": "eda_", "pause": 0.125}, {"key": "w_", "pause": 0.125}, {"key": "e-", "pause": 0.25}, {"key": "wda-", "pause": 0.25}, {"key": "ev-", "pause": 0.25}, {"key": "yda-", "pause": 0.25}, {"key": "e-", "pause": 0.25}, {"key": "wda-", "pause": 0.25}, {"key": "ev_", "pause": 0.125}, {"key": "w_", "pause": 0.125}, {"key": "esm_", "pause": 0.125}, {"key": "w_", "pause": 0.125}, {"key": "e-", "pause": 0.25}, {"key": "wsm-", "pause": 0.25}, {"key": "gv-", "pause": 0.25}, {"key": "wsm-", "pause": 0.25}, {"key": "j-", "pause": 0.25}, {"key": "gsm-", "pause": 0.25}, {"key": "gc-", "pause": 0.25}, {"key": "wsm_", "pause": 0.125}, {"key": "a_", "pause": 0.125}, {"key": "w-", "pause": 0.25}, {"key": "qsm-", "pause": 0.25}, {"key": "wc-", "pause": 0.25}, {"key": "tsm-", "pause": 0.25}, {"key": "t-", "pause": 0.25}, {"key": "wsm-", "pause": 0.25}, {"key": "wn_", "pause": 0.125}, {"key": "e_", "pause": 0.125}, {"key": "wda_", "pause": 0.125}, {"key": "e_", "pause": 0.125}, {"key": "w-", "pause": 0.25}, {"key": "jad-", "pause": 0.25}, {"key": "qnc-", "pause": 0.25}, {"key": "ad-", "pause": 0.25}, {"key": "jxb-", "pause": 0.25}, {"key": "ms-", "pause": 0.25}, {"key": "hv-", "pause": 0.25}, {"key": "eda_", "pause": 0.125}, {"key": "w_", "pause": 0.125}, {"key": "e-", "pause": 0.25}, {"key": "wad-", "pause": 0.25}, {"key": "ev-", "pause": 0.25}, {"key": "yda-", "pause": 0.25}, {"key": "e-", "pause": 0.25}, {"key": "wad-", "pause": 0.25}, {"key": "ev_", "pause": 0.125}, {"key": "w_", "pause": 0.125}, {"key": "esm_", "pause": 0.125}, {"key": "w_", "pause": 0.125}, {"key": "e-", "pause": 0.25}, {"key": "wsm-", "pause": 0.25}, {"key": "gv-", "pause": 0.25}, {"key": "wsm-", "pause": 0.25}, {"key": "j-", "pause": 0.25}, {"key": "gsm-", "pause": 0.25}, {"key": "gc-", "pause": 0.25}, {"key": "wsm_", "pause": 0.125}, {"key": "q_", "pause": 0.125}, {"key": "w0", "pause": 0.5}, {"key": "qsm-", "pause": 0.25}, {"key": "wc-", "pause": 0.25}, {"key": "tsm-", "pause": 0.25}, {"key": "t-", "pause": 0.25}, {"key": "usm-", "pause": 0.25}, {"key": "yn_", "pause": 0.125}, {"key": "u_", "pause": 0.125}, {"key": "yda_", "pause": 0.125}, {"key": "u_", "pause": 0.125}, {"key": "y-", "pause": 0.25}, {"key": "tda-", "pause": 0.25}, {"key": "yn-", "pause": 0.25}, {"key": "hanc-", "pause": 0.25}, {"key": "j", "pause": 0.5}, {"key": "jdvz-", "pause": 0.25}, {"key": "hd-", "pause": 0.25}, {"key": "d-", "pause": 0.25}, {"key": "jdvz-", "pause": 0.25}, {"key": "hdvz-", "pause": 0.25}, {"key": "d-", "pause": 0.25}, {"key": "hdvz-", "pause": 0.25}, {"key": "jd-", "pause": 0.25}, {"key": "qsbx-", "pause": 0.25}, {"key": "js-", "pause": 0.25}, {"key": "d-", "pause": 0.25}, {"key": "qsbx-", "pause": 0.25}, {"key": "jsbx-", "pause": 0.25}, {"key": "d-", "pause": 0.25}, {"key": "jsbx-", "pause": 0.25}, {"key": "qs-", "pause": 0.25}, {"key": "wdnc-", "pause": 0.25}, {"key": "dq-", "pause": 0.25}, {"key": "d-", "pause": 0.25}, {"key": "dwnc-", "pause": 0.25}, {"key": "dqnc-", "pause": 0.25}, {"key": "d-", "pause": 0.25}, {"key": "dqnc-", "pause": 0.25}, {"key": "dw-", "pause": 0.25}, {"key": "qeanc", "pause": 0.5}, {"key": "c", "pause": 0.5}, {"key": "adn", "pause": 0.5}, {"key": "gx", "pause": 0.5}, {"key": "jdvz-", "pause": 0.25}, {"key": "hd-", "pause": 0.25}, {"key": "d-", "pause": 0.25}, {"key": "djvz-", "pause": 0.25}, {"key": "dhvz-", "pause": 0.25}, {"key": "d-", "pause": 0.25}, {"key": "dhvz-", "pause": 0.25}, {"key": "dj-", "pause": 0.25}, {"key": "qsbx-", "pause": 0.25}, {"key": "sj-", "pause": 0.25}, {"key": "d-", "pause": 0.25}, {"key": "sqbx-", "pause": 0.25}, {"key": "sjbx-", "pause": 0.25}, {"key": "d-", "pause": 0.25}, {"key": "sjbx-", "pause": 0.25}, {"key": "qs-", "pause": 0.25}, {"key": "wdnc-", "pause": 0.25}, {"key": "qd-", "pause": 0.25}, {"key": "d-", "pause": 0.25}, {"key": "dwnc-", "pause": 0.25}, {"key": "dqnc-", "pause": 0.25}, {"key": "d-", "pause": 0.25}, {"key": "dqnc-", "pause": 0.25}, {"key": "dj-", "pause": 0.25}, {"key": "hanc", "pause": 0.5}, {"key": "c", "pause": 0.5}, {"key": "dan", "pause": 0.5}, {"key": "bx", "pause": 0.5}, {"key": "evz-", "pause": 0.25}, {"key": "yda_", "pause": 0.125}, {"key": "y_", "pause": 0.125}, {"key": "y-", "pause": 0.25}, {"key": "eda_", "pause": 0.125}, {"key": "e_", "pause": 0.125}, {"key": "ev-", "pause": 0.25}, {"key": "qda_", "pause": 0.125}, {"key": "q_", "pause": 0.125}, {"key": "q-", "pause": 0.25}, {"key": "eda-", "pause": 0.25}, {"key": "evz-", "pause": 0.25}, {"key": "wsj_", "pause": 0.125}, {"key": "w_", "pause": 0.125}, {"key": "w-", "pause": 0.25}, {"key": "qsm-", "pause": 0.25}, {"key": "wgv-", "pause": 0.25}, {"key": "w-", "pause": 0.25}, {"key": "j-", "pause": 0.25}, {"key": "msg-", "pause": 0.25}, {"key": "wc-", "pause": 0.25}, {"key": "tsm_", "pause": 0.125}, {"key": "t_", "pause": 0.125}, {"key": "t-", "pause": 0.25}, {"key": "wsm_", "pause": 0.125}, {"key": "w_", "pause": 0.125}, {"key": "wc-", "pause": 0.25}, {"key": "jsm_", "pause": 0.125}, {"key": "j_", "pause": 0.125}, {"key": "j-", "pause": 0.25}, {"key": "wsm-", "pause": 0.25}, {"key": "wnc-", "pause": 0.25}, {"key": "qda_", "pause": 0.125}, {"key": "q_", "pause": 0.125}, {"key": "q-", "pause": 0.25}, {"key": "jda-", "pause": 0.25}, {"key": "qdan", "pause": 0.5}, {"key": "bx", "pause": 0.5}, {"key": "tx-", "pause": 0.25}, {"key": "rn-", "pause": 0.25}, {"key": "qs-", "pause": 0.25}, {"key": "tf-", "pause": 0.25}, {"key": "h-", "pause": 0.25}, {"key": "r-", "pause": 0.25}, {"key": "rx", "pause": 0.5}, {"key": "rc-", "pause": 0.25}, {"key": "m-", "pause": 0.25}, {"key": "s-", "pause": 0.25}, {"key": "ed-", "pause": 0.25}, {"key": "ed", "pause": 0.5}, {"key": "jc", "pause": 0.5}, {"key": "jn", "pause": 0.5}, {"key": "c", "pause": 0.5}, {"key": "m", "pause": 0.5}, {"key": "a", "pause": 0.5}, {"key": "h+", "pause": 1.0}, {"key": "bx+", "pause": 1.0}, {"key": "hv", "pause": 0.5}, {"key": "e-", "pause": 0.25}, {"key": "w-", "pause": 0.25}, {"key": "eda", "pause": 0.5}, {"key": "w", "pause": 0.5}, {"key": "ehda", "pause": 0.5}, {"key": "y", "pause": 0.5}, {"key": "e", "pause": 0.5}, {"key": "w", "pause": 0.5}, {"key": "ejf-", "pause": 0.25}, {"key": "w-", "pause": 0.25}, {"key": "e-", "pause": 0.25}, {"key": "w-", "pause": 0.25}, {"key": "e", "pause": 0.5}, {"key": "w", "pause": 0.5}, {"key": "w", "pause": 0.5}, {"key": "t+", "pause": 1.0}]}